novita_client/__init__.py
novita_client/exceptions.py
novita_client/novita.py
novita_client/proto.py
novita_client/serializer.py
novita_client/settings.py
novita_client/utils.py
novita_client/version.py
novita_client-0.6.1.dist-info/METADATA
novita_client-0.6.1.dist-info/WHEEL
novita_client-0.6.1.dist-info/licenses/LICENSE
novita_client-0.6.1.dist-info/RECORD
