Metadata-Version: 2.3
Name: novita_client
Version: 0.6.1
Summary: Novita AI Python SDK
Project-URL: Homepage, https://github.com/novita/python-sdk
Project-URL: Bug Tracker, https://discord.gg/nzqq8UScpx
Author-email: Novita AI <novitalabs@gmail.com>
License: MIT License
License-File: LICENSE
Classifier: License :: OSI Approved :: MIT License
Classifier: Programming Language :: Python
Classifier: Programming Language :: Python :: 3
Requires-Python: >=3.6
Requires-Dist: dataclass-wizard>=0.22.2
Requires-Dist: pillow>=10.2.0
Requires-Dist: requests>=2.27.1
